odoo/addons/mobile_app_abstract/README.rst
odoo/addons/mobile_app_abstract/__init__.py
odoo/addons/mobile_app_abstract/__manifest__.py
odoo/addons/mobile_app_abstract/demo/product_product.xml
odoo/addons/mobile_app_abstract/demo/res_groups.xml
odoo/addons/mobile_app_abstract/i18n/fr.po
odoo/addons/mobile_app_abstract/i18n/mobile_app_abstract.pot
odoo/addons/mobile_app_abstract/models/__init__.py
odoo/addons/mobile_app_abstract/models/mobile_app_abstract.py
odoo/addons/mobile_app_abstract/readme/CONTRIBUTORS.rst
odoo/addons/mobile_app_abstract/readme/DESCRIPTION.rst
odoo/addons/mobile_app_abstract/static/description/icon.png
odoo/addons/mobile_app_abstract/static/description/index.html
odoo11_addon_mobile_app_abstract-11.0.2.0.0.99.dev8.dist-info/METADATA
odoo11_addon_mobile_app_abstract-11.0.2.0.0.99.dev8.dist-info/WHEEL
odoo11_addon_mobile_app_abstract-11.0.2.0.0.99.dev8.dist-info/top_level.txt
odoo11_addon_mobile_app_abstract-11.0.2.0.0.99.dev8.dist-info/RECORD
